{\n  "version": 1,\n  "synergies": [\n    {\n      "id": "synergy_goblin_trio",\n      "name": "도깨비 삼총사",\n      "description": "도깨비 기술자, 도깨비 상인, 도깨비 무술가가 함께하면 정비소가 더 활기찬다.",\n      "requiredCompanionIds": ["dokkaebi_engineer", "dokkaebi_merchant", "dokkaebi_martial"],\n      "effects": [\n        { "type": "goldGain", "value": 0.08, "scope": "global" },\n        { "type": "fragmentsGain", "value": 0.05, "scope": "global" }\n      ]\n    },\n    {\n      "id": "synergy_legendary_guardians",\n      "name": "전설의 수호자들",\n      "description": "호랑이, 봉황, 용이 함께하면 강력한 기운이 흐른다.",\n      "requiredCompanionIds": ["tiger_guardian", "phoenix_guardian", "dragon_guardian"],\n      "effects": [\n        { "type": "offlineEfficiency", "value": 0.15, "scope": "offline" },\n        { "type": "goldGain", "value": 0.05, "scope": "global" }\n      ]\n    },\n    {\n      "id": "synergy_spirit_harmony",\n      "name": "영혼의 조화",\n      "description": "여우 영혼과 구미호가 함께하면 신비로운 기운이 흐른다.",\n      "requiredCompanionIds": ["fox_spirit", "nine_tailed_fox"],\n      "effects": [\n        { "type": "passXpGain", "value": 0.12, "scope": "modes" },\n        { "type": "goldGain", "value": 0.03, "scope": "global" }\n      ]\n    },\n    {\n      "id": "synergy_mountain_dwellers",\n      "name": "산의 주민들",\n      "description": "산신령과 산 정령들이 함께하면 산의 축복을 받는다.",\n      "requiredCompanionIds": ["mountain_spirit", "stone_golem", "earth_elemental"],\n      "effects": [\n        { "type": "offlineEfficiency", "value": 0.1, "scope": "offline" },\n        { "type": "fragmentsGain", "value": 0.08, "scope": "global" }\n      ]\n    },\n    {\n      "id": "synergy_water_dancers",\n      "name": "물의 무용수들",\n      "description": "물의 정령들이 함께하면 흐르는 물처럼 순조롭다.",\n      "requiredCompanionIds": ["water_spirit", "river_nymph", "sea_maiden"],\n      "effects": [\n        { "type": "goldGain", "value": 0.07, "scope": "global" },\n        { "type": "passXpGain", "value": 0.08, "scope": "modes" }\n      ]\n    },\n    {\n      "id": "synergy_ancient_scholars",\n      "name": "고대 학자들",\n      "description": "지혜로운 존재들이 함께하면 지식의 빛이 나타난다.",\n      "requiredCompanionIds": ["wise_owl", "ancient_turtle", "scholar_ghost"],\n      "effects": [\n        { "type": "passXpGain", "value": 0.1, "scope": "modes" },\n        { "type": "cosmeticTokenBonus", "value": 0.05, "scope": "global" }\n      ]\n    },\n    {\n      "id": "synergy_celestial_beings",\n      "name": "천상의 존재들",\n      "description": "천상의 존재들이 함께하면 하늘의 축복이 내린다.",\n      "requiredCompanionIds": ["celestial_angel", "star_spirit", "moon_goddess"],\n      "effects": [\n        { "type": "offlineEfficiency", "value": 0.12, "scope": "offline" },\n        { "type": "goldGain", "value": 0.06, "scope": "global" }\n      ]\n    },\n    {\n      "id": "synergy_mischief_makers",\n      "name": "장난꾸러기들",\n      "description": "말썽꾸러기 정령들이 함께하면 정비소가 더 재미있어진다.",\n      "requiredCompanionIds": ["mischief_sprite", "trickster_fox", "chaos_imp"],\n      "effects": [\n        { "type": "goldGain", "value": 0.09, "scope": "global" },\n        { "type": "fragmentsGain", "value": 0.06, "scope": "global" }\n      ]\n    },\n    {\n      "id": "synergy_nature_protectors",\n      "name": "자연의 수호자들",\n      "description": "자연을 지키는 존재들이 함께하면 자연의 힘이 흐른다.",\n      "requiredCompanionIds": ["forest_guardian", "tree_spirit", "nature_fairy"],\n      "effects": [\n        { "type": "offlineEfficiency", "value": 0.08, "scope": "offline" },\n        { "type": "fragmentsGain", "value": 0.1, "scope": "global" }\n      ]\n    },\n    {\n      "id": "synergy_dream_weavers",\n      "name": "꿈의 짜는 자들",\n      "description": "꿈을 짜는 존재들이 함께하면 신비로운 일들이 일어난다.",\n      "requiredCompanionIds": ["dream_weaver", "nightmare_guardian", "sleep_spirit"],\n      "effects": [\n        { "type": "passXpGain", "value": 0.09, "scope": "modes" },\n        { "type": "goldGain", "value": 0.04, "scope": "global" }\n      ]\n    },\n    {\n      "id": "synergy_shadow_dancers",\n      "name": "그림자의 무용수들",\n      "description": "그림자의 존재들이 함께하면 신비로운 기운이 감돈다.",\n      "requiredCompanionIds": ["shadow_dancer", "dark_spirit", "twilight_guardian"],\n      "effects": [\n        { "type": "offlineEfficiency", "value": 0.11, "scope": "offline" },\n        { "type": "cosmeticTokenBonus", "value": 0.08, "scope": "global" }\n      ]\n    },\n    {\n      "id": "synergy_light_bearers",\n      "name": "빛의 운반자들",\n      "description": "빛을 나르는 존재들이 함께하면 밝은 기운이 퍼진다.",\n      "requiredCompanionIds": ["light_bearer", "sun_spirit", "star_guardian"],\n      "effects": [\n        { "type": "goldGain", "value": 0.1, "scope": "global" },\n        { "type": "passXpGain", "value": 0.07, "scope": "modes" }\n      ]\n    }\n  ],\n  "balanceLimits": {\n    "goldGain_max": 0.5,\n    "offlineEfficiency_max": 0.4,\n    "passXpGain_max": 0.3,\n    "fragmentsGain_max": 0.35,\n    "cosmeticTokenBonus_max": 0.2\n  }\n}\n
